lakeside2/__init__.py
lakeside2/lakeside_pb2.py
lakeside2-0.13.dist-info/LICENSE
lakeside2-0.13.dist-info/METADATA
lakeside2-0.13.dist-info/WHEEL
lakeside2-0.13.dist-info/top_level.txt
lakeside2-0.13.dist-info/RECORD
